devious_winrm/__init__.py
devious_winrm/__main__.py
devious_winrm/app.py
devious_winrm/cli.py
devious_winrm/util/__init__.py
devious_winrm/util/bypass_amsi.py
devious_winrm/util/commands.py
devious_winrm/util/completers.py
devious_winrm/util/file_upload_download.py
devious_winrm/util/get_command_output.py
devious_winrm/util/invoke_in_memory.py
devious_winrm/util/kerberos.py
devious_winrm/util/keybinds.py
devious_winrm/util/misc.py
devious_winrm/util/printers.py
devious_winrm/util/binaries/RunasCs.exe
devious_winrm/util/scripts/AMSI-Bypass.ps1.template
devious_winrm/util/scripts/ETW-Patch.ps1.template
devious_winrm/util/scripts/Invoke-In-Memory.ps1
devious_winrm/util/scripts/UploadTo-Memory.ps1
devious_winrm/util/scripts/__init__.py
devious_winrm/util/scripts/copy.ps1
devious_winrm/util/scripts/fetch.ps1
devious_winrm-1.2.1.dist-info/licenses/LICENSE
devious_winrm-1.2.1.dist-info/licenses/NOTICE
devious_winrm-1.2.1.dist-info/METADATA
devious_winrm-1.2.1.dist-info/WHEEL
devious_winrm-1.2.1.dist-info/entry_points.txt
devious_winrm-1.2.1.dist-info/top_level.txt
devious_winrm-1.2.1.dist-info/RECORD
