Metadata-Version: 2.4
Name: Devious-WinRM
Version: 1.2.1
Summary: A Pentester's Powershell Client.
Author-email: Pablo Comino <pablo@pablocomino.com>
Requires-Python: >=3.10
License-File: LICENSE
License-File: NOTICE
Requires-Dist: prompt_toolkit>=3.0.5
Requires-Dist: impacket==0.12.0
Requires-Dist: Pygments>=2.19.1
Requires-Dist: rich>=14.0.0
Requires-Dist: typer>=0.16.0
Requires-Dist: devious-pypsrp[kerberos]
Dynamic: license-file
